LICENSE
README.md
setup.py
pyntfa/__init__.py
pyntfa/ntfa.py
pyntfa/readwrite.py
pyntfa.egg-info/PKG-INFO
pyntfa.egg-info/SOURCES.txt
pyntfa.egg-info/dependency_links.txt
pyntfa.egg-info/not-zip-safe
pyntfa.egg-info/requires.txt
pyntfa.egg-info/top_level.txt
pyntfa/src/main.c
pyntfa/src/ntfa_alloc.c
pyntfa/src/ntfa_blas.c
pyntfa/src/ntfa_conjgrad.c
pyntfa/src/ntfa_decart.c
pyntfa/src/ntfa_divnnsc.c
pyntfa/src/ntfa_ntriangle.c
pyntfa/src/ntfa_ntrianglen.c
pyntfa/src/ntfa_triangle.c
pyntfa/src/ntfa_weight2.c